serverautomation/__init__.py
serverautomation/__main__.py
serverautomation/configuration.py
serverautomation/distrolayer.py
server_automation_setup-0.3.5.dist-info/METADATA
server_automation_setup-0.3.5.dist-info/WHEEL
server_automation_setup-0.3.5.dist-info/entry_points.txt
server_automation_setup-0.3.5.dist-info/top_level.txt
server_automation_setup-0.3.5.dist-info/RECORD
