Metadata-Version: 2.1
Name: server-automation-setup
Version: 0.3.5
Summary: A helper program that will setup a remote server for you
Home-page: https://github.com/miversen33/Server-Automation-Setup
Author: miversen33
Author-email: miversen33@gmail.com
License: UNKNOWN
Platform: UNKNOWN
Classifier: Programming Language :: Python :: 3
Classifier: License :: OSI Approved :: MIT License
Classifier: Operating System :: OS Independent
Requires-Python: >3.0
Requires-Dist: pyyaml
Requires-Dist: fabric
Requires-Dist: pyinvoke
Requires-Dist: paramiko
